toolsql/__init__.py
toolsql/py.typed
toolsql/dbs/__init__.py
toolsql/dbs/db_utils.py
toolsql/dbs/login_utils.py
toolsql/dbs/db_classes/__init__.py
toolsql/dbs/db_classes/abstract_db.py
toolsql/dbs/db_classes/postgresql_db.py
toolsql/dbs/db_classes/sqlite_db.py
toolsql/drivers/__init__.py
toolsql/drivers/driver_utils.py
toolsql/drivers/conn_utils/__init__.py
toolsql/drivers/conn_utils/conn_attributes.py
toolsql/drivers/conn_utils/connect_utils.py
toolsql/drivers/conn_utils/db_config_utils.py
toolsql/drivers/conn_utils/transaction_utils.py
toolsql/drivers/conn_utils/uri_utils.py
toolsql/drivers/driver_classes/__init__.py
toolsql/drivers/driver_classes/abstract_driver.py
toolsql/drivers/driver_classes/aiosqlite_driver.py
toolsql/drivers/driver_classes/connectorx_driver.py
toolsql/drivers/driver_classes/dbapi_driver.py
toolsql/drivers/driver_classes/psycopg_driver.py
toolsql/drivers/driver_classes/sqlite3_driver.py
toolsql/executors/__init__.py
toolsql/executors/ddl_executors/__init__.py
toolsql/executors/ddl_executors/alter_executors.py
toolsql/executors/ddl_executors/create_executors.py
toolsql/executors/ddl_executors/drop_executors.py
toolsql/executors/ddl_executors/metadata_executors.py
toolsql/executors/dml_executors/__init__.py
toolsql/executors/dml_executors/delete_executors.py
toolsql/executors/dml_executors/insert_executors.py
toolsql/executors/dml_executors/select_executors.py
toolsql/executors/dml_executors/update_executors.py
toolsql/executors/summary_executors/__init__.py
toolsql/executors/summary_executors/summary_prints.py
toolsql/executors/summary_executors/summary_usage.py
toolsql/formats/__init__.py
toolsql/formats/encoding_format_utils.py
toolsql/formats/json_format_utils.py
toolsql/formats/row_format_utils.py
toolsql/schemas/__init__.py
toolsql/schemas/datatype_utils.py
toolsql/schemas/shorthand_utils.py
toolsql/spec/__init__.py
toolsql/spec/exceptions.py
toolsql/spec/typedata.py
toolsql/spec/typeguards.py
toolsql/spec/typedefs/__init__.py
toolsql-0.6.4.dist-info/LICENSE
toolsql-0.6.4.dist-info/WHEEL
toolsql-0.6.4.dist-info/METADATA
toolsql-0.6.4.dist-info/RECORD
