Metadata-Version: 2.1
Name: toolsql
Version: 0.6.4
Summary: toolsql is an async+sync sql builder+executor for sqlite+postgres
Requires-Python: >=3.7
Requires-Dist: typing_extensions>=4.2.0
Requires-Dist: toolstr >=0.9.1, <0.10
Requires-Dist: polars >=0.17.2, <0.18
Requires-Dist: aiosqlite >=0.18.0, <0.19
Requires-Dist: psycopg >=3.1.8, <3.2
Requires-Dist: connectorx
